odoo9_addon_pos_return_order-9.0.1.0.0-py2.7-nspkg.pth
odoo9_addon_pos_return_order-9.0.1.0.0.dist-info/DESCRIPTION.rst
odoo9_addon_pos_return_order-9.0.1.0.0.dist-info/METADATA
odoo9_addon_pos_return_order-9.0.1.0.0.dist-info/RECORD
odoo9_addon_pos_return_order-9.0.1.0.0.dist-info/WHEEL
odoo9_addon_pos_return_order-9.0.1.0.0.dist-info/metadata.json
odoo9_addon_pos_return_order-9.0.1.0.0.dist-info/namespace_packages.txt
odoo9_addon_pos_return_order-9.0.1.0.0.dist-info/top_level.txt
odoo_addons/pos_return_order/README.rst
odoo_addons/pos_return_order/__init__.py
odoo_addons/pos_return_order/__openerp__.py
odoo_addons/pos_return_order/demo/product_product.xml
odoo_addons/pos_return_order/i18n/fr.po
odoo_addons/pos_return_order/models/__init__.py
odoo_addons/pos_return_order/models/pos_order.py
odoo_addons/pos_return_order/models/pos_order_line.py
odoo_addons/pos_return_order/models/pos_partial_return_wizard.py
odoo_addons/pos_return_order/models/pos_partial_return_wizard_line.py
odoo_addons/pos_return_order/models/product_template.py
odoo_addons/pos_return_order/static/description/icon.png
odoo_addons/pos_return_order/static/description/initial_pos_order_required.png
odoo_addons/pos_return_order/static/description/partial_return_wizard.png
odoo_addons/pos_return_order/static/description/product_returnable_bottle.png
odoo_addons/pos_return_order/static/description/returned_qty_over_initial.png
odoo_addons/pos_return_order/static/description/sum_returned_qty_over_initial.png
odoo_addons/pos_return_order/static/img/product_returnable_bottle-image.jpg
odoo_addons/pos_return_order/views/action.xml
odoo_addons/pos_return_order/views/pos_order_line_view.xml
odoo_addons/pos_return_order/views/pos_order_view.xml
odoo_addons/pos_return_order/views/pos_partial_return_wizard_view.xml
odoo_addons/pos_return_order/views/product_product_view.xml
