Metadata-Version: 2.0
Name: odoo9-addon-pos-return-order
Version: 9.0.1.0.0
Summary: Point of Sale Return Order
Home-page: http://www.lalouve.net
Author: La Louve, GRAP, Odoo Community Association (OCA)
Author-email: support@odoo-community.org
License: UNKNOWN
Platform: UNKNOWN
Classifier: Programming Language :: Python
Classifier: Framework :: Odoo
Requires-Python: ~=2.7
Requires-Dist: odoo (<9.1a,>=9.0a)
